divisor_clock.vhd
library ieee;
use ieee.std_logic_1164.all;
use ieee.numeric_std.all;

entity divisor_clock is
	port ( clk50MHz : in std_logic;
		rset : in std_logic;
		clk100ms : out std_logic);
	end divisor_clock;

architecture Hardware of divisor_clock is

--signal count : integer := 0;
signal b : std_logic := '0';
begin

 -- clk generation. For 50MHz clock this process generates 1Hz clock.
process(clk50MHz, b)
	variable cnt : integer range 0 to 5000000;
    begin
      if(rising_edge(clk50MHz)) then
       --  if(rset = '1') then
        --   cnt := 0;
       -- else
           cnt := cnt + 1;
       -- end if;
        if(cnt = 4) then
          b <= not b;
          cnt := 0;
        end if;
      end if;
      clk100ms <= b;
    end process;
end;

convLeds.vhd
library IEEE;
use IEEE.std_logic_1164.all;

-- entity
entity convLeds is
  port (
    num : in integer range 0 to 10;
    HEX: out std_logic_vector (7 downto 0)
  );
end convLeds;

-- architecture
architecture hardware of convLeds is
begin
  proc:process(num)
    begin
      case num is
        when 0 => HEX <= "10000001"; -- 0
        when 1 => HEX <= "11001111"; -- 1
        when 2 => HEX <= "10010010"; -- 2
        when 3 => HEX <= "10000110"; -- 3
        when 4 => HEX <= "11001100"; -- 4
        when 5 => HEX <= "10100100"; -- 5
        when 6 => HEX <= "10100000"; -- 6
        when 7 => HEX <= "10001111"; -- 7
        when 8 => HEX <= "10000000"; -- 8
        when 9 => HEX <= "10000100"; -- 9
        when others => HEX <= "11111111"; --DELIGADO
      end case;
    end process proc;
end hardware;

calc.vhd
library IEEE;
use IEEE.std_logic_1164.all;
use std.standard.all;
use ieee.numeric_std.all;

-- entity
entity calc is
  port (
    reset, clk, enterN, enterS : in std_logic;
    numero : in std_logic_vector(3 downto 0);
    sinal : in std_logic_vector(1 downto 0);
    HEX0, HEX1, HEX2, HEX3 : out std_logic_vector (7 downto 0));
end calc;

-- architecture
architecture hardware of calc is

  component divisor_clock is
    port (clk50MHz : in std_logic;
          rset : in std_logic;
          clk100ms : out std_logic);
  end component;

  component convLeds is
    port (
      num : in integer range 0 to 10;
      HEX : out std_logic_vector (7 downto 0));
  end component;

  type pilhaNu is array (natural range <>) of integer range -999 to 999;
  type state_type is (US, UN, DN, DS); -- Us- UP sinal, UN- UP Numero ..
  signal PS, PN : state_type; --estados atuais do sinal e numero
  signal PilhaNumero : pilhaNu (0 to 10);
  signal unid, dec, cent, init : integer range 0 to 10 := 10; -- numero para os displays 
  signal clk100: std_logic := '0';  
begin

  --Cria um digito para cada display
  x1 : convLeds port map(num => unid, HEX => HEX0);
  x2 : convLeds port map(num => dec, HEX => HEX1);
  x3 : convLeds port map(num => cent, HEX => HEX2);
  x4 : divisor_clock port map(clk50MHz =>clk, rset=>reset, clk100ms=>clk100);

  sync_proc : process (clk100, reset)
    variable cnt : integer range -1 to 10 := - 1;
  begin
    if (rising_edge(clk100)) then
      if (reset = '1' or init = 10) then
        init <= 0;
        unid <= 0;
        dec <= 10;
        cent <= 10;
        cnt := -1;
        HEX3 <= "11111111"; -- DESLIGA O HEX3

        -- limpa as posições da pilha
        for i in 0 to 10 loop 
          PilhaNumero(i) <= 0;
        end loop;

        if(enterN = '0') then
          PN <= DN;
        else
          PN <= UN;
        end if;
        
        if(enterS = '0') then
          PS <= DS;
        else
          PS <= US; 
        end if;

      elsif (enterN = '1' and PN = DN) then
        PilhaNumero(cnt+1) <= to_integer(unsigned(numero)); --converter o número da entrada para decimal
        cnt := cnt + 1;
        init <= 1;
        PN <= UN;
      elsif (enterN = '0' and PN = UN) then
        PN <= DN;

      elsif (enterS = '1' and PS = DS and cnt > -1) then
        -- realiza as operacoes e joga o resultado na pilha
          if (sinal = "00" and cnt > 0) then --verifica se for o sinal de +
            PilhaNumero(cnt - 1) <= (PilhaNumero(cnt - 1) + PilhaNumero(cnt));
            init <= 1;
            cnt := cnt - 1;
          elsif (sinal = "01" and cnt > 0) then --verifica se for o sinal de -
            PilhaNumero(cnt - 1) <= (PilhaNumero(cnt - 1) - PilhaNumero(cnt));
            init <= 1;
            cnt := cnt - 1;
          elsif (sinal = "10") then --verifica se for o sinal de uma operacao de deslocamento
            PilhaNumero(cnt) <= (PilhaNumero(cnt)*2);
            init <= 1;
          elsif (sinal = "11") then --verifica se for o sinal de >> (deslocamento para direita)
            PilhaNumero(cnt) <= (PilhaNumero(cnt)/2);
            init <=1;
          end if;
          PS <= US;
      elsif (enterS = '0' and PS = US) then
        PS <= DS; -- Down state
      end if;

      if(init = 1 ) then
        init <= 0;
        if(PilhaNumero(cnt)<0) then --instancia display negativos

          if(PilhaNumero(cnt)<-99) then
            cent <= PilhaNumero(cnt)/(-100);
            dec <= (PilhaNumero(cnt)*(-1)-(PilhaNumero(cnt)/(-100))*100)/10;
          elsif (PilhaNumero(cnt)< -9) then
            cent <= 10; --deliga o HEX2
            dec <= PilhaNumero(cnt)/(-10);
          else
            cent <= 10; --deliga o HEX2
            dec <= 10; --deliga o HEX1
          end if;

          HEX3 <= "10111111"; --coloca o sinal -
          unid <= PilhaNumero(cnt)*(-1) mod 10;

        else --instância display positivo

          if(PilhaNumero(cnt)>99) then
            cent <= PilhaNumero(cnt)/100;
            dec <= (PilhaNumero(cnt)-(PilhaNumero(cnt)/100)*100)/10;
          elsif(PilhaNumero(cnt)>9) then
            cent <= 10; --deliga o HEX2
            dec <= PilhaNumero(cnt)/10;
          else
            cent <= 10; --deliga o HEX2
            dec <= 10; --deliga o HEX1
          end if;

          unid <= PilhaNumero(cnt) mod 10;
          HEX3 <= "11111111";
        end if;

      end if;
    end if;  
  end process sync_proc;
end hardware;

tb_calc.vhd
-- library declaration
library IEEE;
use IEEE.std_logic_1164.all;

-- top-level entity
entity tb_calc is end entity;

-- architecture
architecture hardware of tb_calc is
  -- component declaration

  component calc is
    port (
      reset, clk, enterN, enterS: in std_logic;
      numero : in std_logic_vector(3 downto 0);
      sinal : in std_logic_vector(1 downto 0);
      HEX0, HEX1, HEX2, HEX3: out std_logic_vector (7 downto 0)
    );
  end component;

  constant PERIODO : time := 20 ns;
  signal ENT_CLK : std_logic := '0'; -- deve ser inicializado
  signal ENT_CLK_ENABLE : std_logic := '1'; -- Sinal de Enable do clock só para efeito de controle do fim da simulação
  signal ENT_RESET, ENT_ENTERN, ENT_ENTERS: std_logic;
  signal ENT_NUM : std_logic_vector(3 downto 0);
  signal ENT_SINAL : std_logic_vector(1 downto 0);
  signal ENT_H0, ENT_H1, ENT_H2, ENT_H3: std_logic_vector (7 downto 0);

begin
  -- geração do clock com periodo PERIODO
  ENT_CLK <= ENT_CLK_ENABLE and not ENT_CLK after PERIODO/2;
  ENT_CLK_ENABLE <= '1', '0' after 250*PERIODO; -- a simulação termina após transcorrer 20 períodos de clock.

  -- instanciação do DUT, que nesse exemplo é um ffd
  DUT : calc port map(clk => ENT_CLK, reset => ENT_RESET, numero => ENT_NUM, sinal => ENT_SINAL, enterN => ENT_ENTERN, enterS => ENT_ENTERS,
                       HEX0 => ENT_H0, HEX1 => ENT_H1, HEX2 => ENT_H2, HEX3 => ENT_H3);
  -- a partir daqui declaro os estímulos de entrada, ou a injecao de sinais
  -- um process para o reset
  stimulus: process
  begin
    ENT_RESET <= '1';
    wait for 12 * PERIODO;
    ENT_RESET <= '0';
    wait for 12 * PERIODO;
    ENT_ENTERN <= '0';
    ENT_ENTERS <= '0';
    ENT_NUM <= "0101";
    wait for 12*PERIODO;
    ENT_ENTERN <= '1';
    wait for 12*PERIODO;
    ENT_ENTERN <= '0';
    wait for 12*PERIODO;
    ENT_NUM <= "0110";
    ENT_ENTERN <= '1';
    wait for 12*PERIODO;
    ENT_SINAL <= "10"; --DESLOCAMENTO PARA ESQUERDA
    ENT_ENTERS <= '1';
    wait for 12*PERIODO;
    ENT_ENTERS <= '0';
    wait for 12*PERIODO;
    ENT_ENTERN <= '0';
    ENT_SINAL <= "01"; --ADICAO
    ENT_ENTERS <= '1';
    wait for 12*PERIODO;
    ENT_ENTERS <= '0';
    wait for 3*PERIODO;
    ENT_NUM <= "1000";
    ENT_ENTERN <= '1';
    wait for 13*PERIODO;
    ENT_ENTERN <= '0';
    ENT_ENTERS <= '1';
    ENT_SINAL <= "01"; -- SUBTRACAO
    wait for 13*PERIODO;
    ENT_ENTERN <= '0';
    ENT_ENTERS <= '0';
    ENT_RESET <= '1';
    wait for 13*PERIODO;
    ENT_RESET <= '0';
    wait for 12*PERIODO;
    ENT_NUM <= "1011";
    ENT_ENTERN <= '1';
    wait;
  end process stimulus;
end architecture;

tb_calc.vcd
$date
  Sun Dec 11 17:26:48 2022
$end
$version
  GHDL v0
$end
$timescale
  1 fs
$end
$scope module standard $end
$upscope $end
$scope module std_logic_1164 $end
$upscope $end
$scope module numeric_std $end
$upscope $end
$scope module tb_calc $end
$var reg 1 ! ent_clk $end
$var reg 1 " ent_clk_enable $end
$var reg 1 # ent_reset $end
$var reg 1 $ ent_entern $end
$var reg 1 % ent_enters $end
$var reg 4 & ent_num[3:0] $end
$var reg 2 ' ent_sinal[1:0] $end
$var reg 8 ( ent_h0[7:0] $end
$var reg 8 ) ent_h1[7:0] $end
$var reg 8 * ent_h2[7:0] $end
$var reg 8 + ent_h3[7:0] $end
$scope module dut $end
$var reg 1 , reset $end
$var reg 1 - clk $end
$var reg 1 . entern $end
$var reg 1 / enters $end
$var reg 4 0 numero[3:0] $end
$var reg 2 1 sinal[1:0] $end
$var reg 8 2 hex0[7:0] $end
$var reg 8 3 hex1[7:0] $end
$var reg 8 4 hex2[7:0] $end
$var reg 8 5 hex3[7:0] $end
$comment ps is not handled $end
$comment pn is not handled $end
$comment pilhanumero is not handled $end
$var integer 32 6 unid $end
$var integer 32 7 dec $end
$var integer 32 8 cent $end
$var integer 32 9 init $end
$var reg 1 : clk100 $end
$scope module x1 $end
$var integer 32 ; num $end
$var reg 8 < hex[7:0] $end
$upscope $end
$scope module x2 $end
$var integer 32 = num $end
$var reg 8 > hex[7:0] $end
$upscope $end
$scope module x3 $end
$var integer 32 ? num $end
$var reg 8 @ hex[7:0] $end
$upscope $end
$scope module x4 $end
$var reg 1 A clk50mhz $end
$var reg 1 B rset $end
$var reg 1 C clk100ms $end
$var reg 1 D b $end
$upscope $end
$upscope $end
$upscope $end
$enddefinitions $end
#0
0!
1"
1#
U$
U%
bUUUU &
bUU '
b11111111 (
b11111111 )
b11111111 *
bUUUUUUUU +
1,
0-
U.
U/
bUUUU 0
bUU 1
b11111111 2
b11111111 3
b11111111 4
bUUUUUUUU 5
b1010 6
b1010 7
b1010 8
b1010 9
0:
b1010 ;
b11111111 <
b1010 =
b11111111 >
b1010 ?
b11111111 @
0A
1B
0C
0D
#10000000
1!
1-
1A
#20000000
0!
0-
0A
#30000000
1!
1-
1A
#40000000
0!
0-
0A
#50000000
1!
1-
1A
#60000000
0!
0-
0A
#70000000
1!
b11000000 (
b11111111 +
1-
b11000000 2
b11111111 5
b0 6
b0 9
1:
b0 ;
b11000000 <
1A
1C
1D
#80000000
0!
0-
0A
#90000000
1!
1-
1A
#100000000
0!
0-
0A
#110000000
1!
1-
1A
#120000000
0!
0-
0A
#130000000
1!
1-
1A
#140000000
0!
0-
0A
#150000000
1!
1-
0:
1A
0C
0D
#160000000
0!
0-
0A
#170000000
1!
1-
1A
#180000000
0!
0-
0A
#190000000
1!
1-
1A
#200000000
0!
0-
0A
#210000000
1!
1-
1A
#220000000
0!
0-
0A
#230000000
1!
1-
1:
1A
1C
1D
#240000000
0!
0#
0,
0-
0A
0B
#250000000
1!
1-
1A
#260000000
0!
0-
0A
#270000000
1!
1-
1A
#280000000
0!
0-
0A
#290000000
1!
1-
1A
#300000000
0!
0-
0A
#310000000
1!
1-
0:
1A
0C
0D
#320000000
0!
0-
0A
#330000000
1!
1-
1A
#340000000
0!
0-
0A
#350000000
1!
1-
1A
#360000000
0!
0-
0A
#370000000
1!
1-
1A
#380000000
0!
0-
0A
#390000000
1!
1-
1:
1A
1C
1D
#400000000
0!
0-
0A
#410000000
1!
1-
1A
#420000000
0!
0-
0A
#430000000
1!
1-
1A
#440000000
0!
0-
0A
#450000000
1!
1-
1A
#460000000
0!
0-
0A
#470000000
1!
1-
0:
1A
0C
0D
#480000000
0!
0$
0%
b0101 &
0-
0.
0/
b0101 0
0A
#490000000
1!
1-
1A
#500000000
0!
0-
0A
#510000000
1!
1-
1A
#520000000
0!
0-
0A
#530000000
1!
1-
1A
#540000000
0!
0-
0A
#550000000
1!
1-
1:
1A
1C
1D
#560000000
0!
0-
0A
#570000000
1!
1-
1A
#580000000
0!
0-
0A
#590000000
1!
1-
1A
#600000000
0!
0-
0A
#610000000
1!
1-
1A
#620000000
0!
0-
0A
#630000000
1!
1-
0:
1A
0C
0D
#640000000
0!
0-
0A
#650000000
1!
1-
1A
#660000000
0!
0-
0A
#670000000
1!
1-
1A
#680000000
0!
0-
0A
#690000000
1!
1-
1A
#700000000
0!
0-
0A
#710000000
1!
1-
1:
1A
1C
1D
#720000000
0!
1$
0-
1.
0A
#730000000
1!
1-
1A
#740000000
0!
0-
0A
#750000000
1!
1-
1A
#760000000
0!
0-
0A
#770000000
1!
1-
1A
#780000000
0!
0-
0A
#790000000
1!
1-
0:
1A
0C
0D
#800000000
0!
0-
0A
#810000000
1!
1-
1A
#820000000
0!
0-
0A
#830000000
1!
1-
1A
#840000000
0!
0-
0A
#850000000
1!
1-
1A
#860000000
0!
0-
0A
#870000000
1!
1-
b1 9
1:
1A
1C
1D
#880000000
0!
0-
0A
#890000000
1!
1-
1A
#900000000
0!
0-
0A
#910000000
1!
1-
1A
#920000000
0!
0-
0A
#930000000
1!
1-
1A
#940000000
0!
0-
0A
#950000000
1!
1-
0:
1A
0C
0D
#960000000
0!
0-
0A
#970000000
1!
1-
1A
#980000000
0!
0-
0A
#990000000
1!
1-
1A
#1000000000
0!
0$
0-
0.
0A
#1010000000
1!
1-
1A
#1020000000
0!
0-
0A
#1030000000
1!
b10010010 (
1-
b10010010 2
b101 6
b0 9
1:
b101 ;
b10010010 <
1A
1C
1D
#1040000000
0!
0-
0A
#1050000000
1!
1-
1A
#1060000000
0!
0-
0A
#1070000000
1!
1-
1A
#1080000000
0!
0-
0A
#1090000000
1!
1-
1A
#1100000000
0!
0-
0A
#1110000000
1!
1-
0:
1A
0C
0D
#1120000000
0!
0-
0A
#1130000000
1!
1-
1A
#1140000000
0!
0-
0A
#1150000000
1!
1-
1A
#1160000000
0!
0-
0A
#1170000000
1!
1-
1A
#1180000000
0!
0-
0A
#1190000000
1!
1-
1:
1A
1C
1D
#1200000000
0!
0-
0A
#1210000000
1!
1-
1A
#1220000000
0!
0-
0A
#1230000000
1!
1-
1A
#1240000000
0!
1$
b0110 &
0-
1.
b0110 0
0A
#1250000000
1!
1-
1A
#1260000000
0!
b10 '
0-
b10 1
0A
#1270000000
1!
1-
0:
1A
0C
0D
#1280000000
0!
0-
0A
#1290000000
1!
1-
1A
#1300000000
0!
0-
0A
#1310000000
1!
1-
1A
#1320000000
0!
0-
0A
#1330000000
1!
1-
1A
#1340000000
0!
0-
0A
#1350000000
1!
1-
b1 9
1:
1A
1C
1D
#1360000000
0!
0-
0A
#1370000000
1!
1-
1A
#1380000000
0!
0-
0A
#1390000000
1!
1-
1A
#1400000000
0!
0-
0A
#1410000000
1!
1-
1A
#1420000000
0!
0-
0A
#1430000000
1!
1-
0:
1A
0C
0D
#1440000000
0!
0-
0A
#1450000000
1!
1-
1A
#1460000000
0!
0-
0A
#1470000000
1!
1-
1A
#1480000000
0!
1%
0-
1/
0A
#1490000000
1!
1-
1A
#1500000000
0!
0-
0A
#1510000000
1!
b10000010 (
1-
b10000010 2
b110 6
b0 9
1:
b110 ;
b10000010 <
1A
1C
1D
#1520000000
0!
0-
0A
#1530000000
1!
1-
1A
#1540000000
0!
0-
0A
#1550000000
1!
1-
1A
#1560000000
0!
0-
0A
#1570000000
1!
1-
1A
#1580000000
0!
0-
0A
#1590000000
1!
1-
0:
1A
0C
0D
#1600000000
0!
0-
0A
#1610000000
1!
1-
1A
#1620000000
0!
0-
0A
#1630000000
1!
1-
1A
#1640000000
0!
0-
0A
#1650000000
1!
1-
1A
#1660000000
0!
0-
0A
#1670000000
1!
1-
1:
1A
1C
1D
#1680000000
0!
0-
0A
#1690000000
1!
1-
1A
#1700000000
0!
0-
0A
#1710000000
1!
1-
1A
#1720000000
0!
0%
0-
0/
0A
#1730000000
1!
1-
1A
#1740000000
0!
0-
0A
#1750000000
1!
1-
0:
1A
0C
0D
#1760000000
0!
0-
0A
#1770000000
1!
1-
1A
#1780000000
0!
0-
0A
#1790000000
1!
1-
1A
#1800000000
0!
0-
0A
#1810000000
1!
1-
1A
#1820000000
0!
0-
0A
#1830000000
1!
1-
1:
1A
1C
1D
#1840000000
0!
0-
0A
#1850000000
1!
1-
1A
#1860000000
0!
0-
0A
#1870000000
1!
1-
1A
#1880000000
0!
0-
0A
#1890000000
1!
1-
1A
#1900000000
0!
0-
0A
#1910000000
1!
1-
0:
1A
0C
0D
#1920000000
0!
0-
0A
#1930000000
1!
1-
1A
#1940000000
0!
0-
0A
#1950000000
1!
1-
1A
#1960000000
0!
0$
1%
b01 '
0-
0.
1/
b01 1
0A
#1970000000
1!
1-
1A
#1980000000
0!
0-
0A
#1990000000
1!
1-
1:
1A
1C
1D
#2000000000
0!
0-
0A
#2010000000
1!
1-
1A
#2020000000
0!
0-
0A
#2030000000
1!
1-
1A
#2040000000
0!
0-
0A
#2050000000
1!
1-
1A
#2060000000
0!
0-
0A
#2070000000
1!
1-
0:
1A
0C
0D
#2080000000
0!
0-
0A
#2090000000
1!
1-
1A
#2100000000
0!
0-
0A
#2110000000
1!
1-
1A
#2120000000
0!
0-
0A
#2130000000
1!
1-
1A
#2140000000
0!
0-
0A
#2150000000
1!
1-
b1 9
1:
1A
1C
1D
#2160000000
0!
0-
0A
#2170000000
1!
1-
1A
#2180000000
0!
0-
0A
#2190000000
1!
1-
1A
#2200000000
0!
0%
0-
0/
0A
#2210000000
1!
1-
1A
#2220000000
0!
0-
0A
#2230000000
1!
1-
0:
1A
0C
0D
#2240000000
0!
0-
0A
#2250000000
1!
1-
1A
#2260000000
0!
1$
b1000 &
0-
1.
b1000 0
0A
#2270000000
1!
1-
1A
#2280000000
0!
0-
0A
#2290000000
1!
1-
1A
#2300000000
0!
0-
0A
#2310000000
1!
b10100100 (
b11111001 )
1-
b10100100 2
b11111001 3
b10 6
b1 7
b0 9
1:
b10 ;
b10100100 <
b1 =
b11111001 >
1A
1C
1D
#2320000000
0!
0-
0A
#2330000000
1!
1-
1A
#2340000000
0!
0-
0A
#2350000000
1!
1-
1A
#2360000000
0!
0-
0A
#2370000000
1!
1-
1A
#2380000000
0!
0-
0A
#2390000000
1!
1-
0:
1A
0C
0D
#2400000000
0!
0-
0A
#2410000000
1!
1-
1A
#2420000000
0!
0-
0A
#2430000000
1!
1-
1A
#2440000000
0!
0-
0A
#2450000000
1!
1-
1A
#2460000000
0!
0-
0A
#2470000000
1!
1-
1:
1A
1C
1D
#2480000000
0!
0-
0A
#2490000000
1!
1-
1A
#2500000000
0!
0-
0A
#2510000000
1!
1-
1A
#2520000000
0!
0$
1%
0-
0.
1/
0A
#2530000000
1!
1-
1A
#2540000000
0!
0-
0A
#2550000000
1!
1-
0:
1A
0C
0D
#2560000000
0!
0-
0A
#2570000000
1!
1-
1A
#2580000000
0!
0-
0A
#2590000000
1!
1-
1A
#2600000000
0!
0-
0A
#2610000000
1!
1-
1A
#2620000000
0!
0-
0A
#2630000000
1!
1-
1:
1A
1C
1D
#2640000000
0!
0-
0A
#2650000000
1!
1-
1A
#2660000000
0!
0-
0A
#2670000000
1!
1-
1A
#2680000000
0!
0-
0A
#2690000000
1!
1-
1A
#2700000000
0!
0-
0A
#2710000000
1!
1-
0:
1A
0C
0D
#2720000000
0!
0-
0A
#2730000000
1!
1-
1A
#2740000000
0!
0-
0A
#2750000000
1!
1-
1A
#2760000000
0!
0-
0A
#2770000000
1!
1-
1A
#2780000000
0!
1#
0%
1,
0-
0/
0A
1B
#2790000000
1!
b11000000 (
b11111111 )
1-
b11000000 2
b11111111 3
b0 6
b1010 7
1:
b0 ;
b11000000 <
b1010 =
b11111111 >
1A
1C
1D
#2800000000
0!
0-
0A
#2810000000
1!
1-
1A
#2820000000
0!
0-
0A
#2830000000
1!
1-
1A
#2840000000
0!
0-
0A
#2850000000
1!
1-
1A
#2860000000
0!
0-
0A
#2870000000
1!
1-
0:
1A
0C
0D
#2880000000
0!
0-
0A
#2890000000
1!
1-
1A
#2900000000
0!
0-
0A
#2910000000
1!
1-
1A
#2920000000
0!
0-
0A
#2930000000
1!
1-
1A
#2940000000
0!
0-
0A
#2950000000
1!
1-
1:
1A
1C
1D
#2960000000
0!
0-
0A
#2970000000
1!
1-
1A
#2980000000
0!
0-
0A
#2990000000
1!
1-
1A
#3000000000
0!
0-
0A
#3010000000
1!
1-
1A
#3020000000
0!
0-
0A
#3030000000
1!
1-
0:
1A
0C
0D
#3040000000
0!
0#
0,
0-
0A
0B
#3050000000
1!
1-
1A
#3060000000
0!
0-
0A
#3070000000
1!
1-
1A
#3080000000
0!
0-
0A
#3090000000
1!
1-
1A
#3100000000
0!
0-
0A
#3110000000
1!
1-
1:
1A
1C
1D
#3120000000
0!
0-
0A
#3130000000
1!
1-
1A
#3140000000
0!
0-
0A
#3150000000
1!
1-
1A
#3160000000
0!
0-
0A
#3170000000
1!
1-
1A
#3180000000
0!
0-
0A
#3190000000
1!
1-
0:
1A
0C
0D
#3200000000
0!
0-
0A
#3210000000
1!
1-
1A
#3220000000
0!
0-
0A
#3230000000
1!
1-
1A
#3240000000
0!
0-
0A
#3250000000
1!
1-
1A
#3260000000
0!
0-
0A
#3270000000
1!
1-
1:
1A
1C
1D
#3280000000
0!
1$
b1011 &
0-
1.
b1011 0
0A
#3290000000
1!
1-
1A
#3300000000
0!
0-
0A
#3310000000
1!
1-
1A
#3320000000
0!
0-
0A
#3330000000
1!
1-
1A
#3340000000
0!
0-
0A
#3350000000
1!
1-
0:
1A
0C
0D
#3360000000
0!
0-
0A
#3370000000
1!
1-
1A
#3380000000
0!
0-
0A
#3390000000
1!
1-
1A
#3400000000
0!
0-
0A
#3410000000
1!
1-
1A
#3420000000
0!
0-
0A
#3430000000
1!
1-
b1 9
1:
1A
1C
1D
#3440000000
0!
0-
0A
#3450000000
1!
1-
1A
#3460000000
0!
0-
0A
#3470000000
1!
1-
1A
#3480000000
0!
0-
0A
#3490000000
1!
1-
1A
#3500000000
0!
0-
0A
#3510000000
1!
1-
0:
1A
0C
0D
#3520000000
0!
0-
0A
#3530000000
1!
1-
1A
#3540000000
0!
0-
0A
#3550000000
1!
1-
1A
#3560000000
0!
0-
0A
#3570000000
1!
1-
1A
#3580000000
0!
0-
0A
#3590000000
1!
b11111001 (
b11111001 )
1-
b11111001 2
b11111001 3
b1 6
b1 7
b0 9
1:
b1 ;
b11111001 <
b1 =
b11111001 >
1A
1C
1D
#3600000000
0!
0-
0A
#3610000000
1!
1-
1A
#3620000000
0!
0-
0A
#3630000000
1!
1-
1A
#3640000000
0!
0-
0A
#3650000000
1!
1-
1A
#3660000000
0!
0-
0A
#3670000000
1!
1-
0:
1A
0C
0D
#3680000000
0!
0-
0A
#3690000000
1!
1-
1A
#3700000000
0!
0-
0A
#3710000000
1!
1-
1A
#3720000000
0!
0-
0A
#3730000000
1!
1-
1A
#3740000000
0!
0-
0A
#3750000000
1!
1-
1:
1A
1C
1D
#3760000000
0!
0-
0A
#3770000000
1!
1-
1A
#3780000000
0!
0-
0A
#3790000000
1!
1-
1A
#3800000000
0!
0-
0A
#3810000000
1!
1-
1A
#3820000000
0!
0-
0A
#3830000000
1!
1-
0:
1A
0C
0D
#3840000000
0!
0-
0A
#3850000000
1!
1-
1A
#3860000000
0!
0-
0A
#3870000000
1!
1-
1A
#3880000000
0!
0-
0A
#3890000000
1!
1-
1A
#3900000000
0!
0-
0A
#3910000000
1!
1-
1:
1A
1C
1D
#3920000000
0!
0-
0A
#3930000000
1!
1-
1A
#3940000000
0!
0-
0A
#3950000000
1!
1-
1A
#3960000000
0!
0-
0A
#3970000000
1!
1-
1A
#3980000000
0!
0-
0A
#3990000000
1!
1-
0:
1A
0C
0D
#4000000000
0!
0-
0A
#4010000000
1!
1-
1A
#4020000000
0!
0-
0A
#4030000000
1!
1-
1A
#4040000000
0!
0-
0A
#4050000000
1!
1-
1A
#4060000000
0!
0-
0A
#4070000000
1!
1-
1:
1A
1C
1D
#4080000000
0!
0-
0A
#4090000000
1!
1-
1A
#4100000000
0!
0-
0A
#4110000000
1!
1-
1A
#4120000000
0!
0-
0A
#4130000000
1!
1-
1A
#4140000000
0!
0-
0A
#4150000000
1!
1-
0:
1A
0C
0D
#4160000000
0!
0-
0A
#4170000000
1!
1-
1A
#4180000000
0!
0-
0A
#4190000000
1!
1-
1A
#4200000000
0!
0-
0A
#4210000000
1!
1-
1A
#4220000000
0!
0-
0A
#4230000000
1!
1-
1:
1A
1C
1D
#4240000000
0!
0-
0A
#4250000000
1!
1-
1A
#4260000000
0!
0-
0A
#4270000000
1!
1-
1A
#4280000000
0!
0-
0A
#4290000000
1!
1-
1A
#4300000000
0!
0-
0A
#4310000000
1!
1-
0:
1A
0C
0D
#4320000000
0!
0-
0A
#4330000000
1!
1-
1A
#4340000000
0!
0-
0A
#4350000000
1!
1-
1A
#4360000000
0!
0-
0A
#4370000000
1!
1-
1A
#4380000000
0!
0-
0A
#4390000000
1!
1-
1:
1A
1C
1D
#4400000000
0!
0-
0A
#4410000000
1!
1-
1A
#4420000000
0!
0-
0A
#4430000000
1!
1-
1A
#4440000000
0!
0-
0A
#4450000000
1!
1-
1A
#4460000000
0!
0-
0A
#4470000000
1!
1-
0:
1A
0C
0D
#4480000000
0!
0-
0A
#4490000000
1!
1-
1A
#4500000000
0!
0-
0A
#4510000000
1!
1-
1A
#4520000000
0!
0-
0A
#4530000000
1!
1-
1A
#4540000000
0!
0-
0A
#4550000000
1!
1-
1:
1A
1C
1D
#4560000000
0!
0-
0A
#4570000000
1!
1-
1A
#4580000000
0!
0-
0A
#4590000000
1!
1-
1A
#4600000000
0!
0-
0A
#4610000000
1!
1-
1A
#4620000000
0!
0-
0A
#4630000000
1!
1-
0:
1A
0C
0D
#4640000000
0!
0-
0A
#4650000000
1!
1-
1A
#4660000000
0!
0-
0A
#4670000000
1!
1-
1A
#4680000000
0!
0-
0A
#4690000000
1!
1-
1A
#4700000000
0!
0-
0A
#4710000000
1!
1-
1:
1A
1C
1D
#4720000000
0!
0-
0A
#4730000000
1!
1-
1A
#4740000000
0!
0-
0A
#4750000000
1!
1-
1A
#4760000000
0!
0-
0A
#4770000000
1!
1-
1A
#4780000000
0!
0-
0A
#4790000000
1!
1-
0:
1A
0C
0D
#4800000000
0!
0-
0A
#4810000000
1!
1-
1A
#4820000000
0!
0-
0A
#4830000000
1!
1-
1A
#4840000000
0!
0-
0A
#4850000000
1!
1-
1A
#4860000000
0!
0-
0A
#4870000000
1!
1-
1:
1A
1C
1D
#4880000000
0!
0-
0A
#4890000000
1!
1-
1A
#4900000000
0!
0-
0A
#4910000000
1!
1-
1A
#4920000000
0!
0-
0A
#4930000000
1!
1-
1A
#4940000000
0!
0-
0A
#4950000000
1!
1-
0:
1A
0C
0D
