convLeds.vhd
library IEEE;
use IEEE.std_logic_1164.all;

-- entity
entity convLeds is
  port (
    num : in integer range 0 to 10;
    HEX: out std_logic_vector (7 downto 0)
  );
end convLeds;

-- architecture
architecture hardware of convLeds is
begin
  proc:process(num)
    begin
      case num is
        when 0 => HEX <= "11000000"; -- 0 
        when 1 => HEX <= "11111001"; -- 1
        when 2 => HEX <= "10100100"; -- 2
        when 3 => HEX <= "10110000"; -- 3
        when 4 => HEX <= "10011001"; -- 4
        when 5 => HEX <= "10010010"; -- 5
        when 6 => HEX <= "10000010"; -- 6
        when 7 => HEX <= "11111000"; -- 7
        when 8 => HEX <= "10000000"; -- 8
        when 9 => HEX <= "10010000"; -- 9
        when others => HEX <= "11111111"; --DELIGADO
      end case;
    end process proc;
end hardware;

calc.vhd
library IEEE;
use IEEE.std_logic_1164.all;
use std.standard.all;
use ieee.numeric_std.all;

-- entity
entity calc is
  port (
    reset, clk, enterN, enterS : in std_logic;
    numero : in std_logic_vector(3 downto 0);
    sinal : in std_logic_vector(1 downto 0);
    HEX0, HEX1, HEX2, HEX3 : out std_logic_vector (7 downto 0));
end calc;

-- architecture
architecture hardware of calc is
  component convLeds is
    port (
      num : in integer range 0 to 10;
      HEX : out std_logic_vector (7 downto 0));
  end component;

  type pilhaNu is array (natural range <>) of integer range -999 to 999;
  type state_type is (US, UN, DN, DS); -- Us- UP sinal, UN- UP Numero ..
  signal PS, PN : state_type; --estados atuais do sinal e numero
  signal PilhaNumero : pilhaNu (0 to 10);
  signal unid, dec, cent, init : integer range 0 to 10 := 10; -- numero para os displays   
begin

  --Cria um digito para cada display
  x1 : convLeds port map(num => unid, HEX => HEX0);
  x2 : convLeds port map(num => dec, HEX => HEX1);
  x3 : convLeds port map(num => cent, HEX => HEX2);

  sync_proc : process (clk, reset)
    variable cnt : integer range -1 to 10 := - 1;
  begin
    if (rising_edge(clk)) then
      if (reset = '1' or init = 10) then
        init <= 0;
        unid <= 0;
        dec <= 10;
        cent <= 10;
        cnt := -1;
        HEX3 <= "11111111"; -- DESLIGA O HEX3

        -- limpa as posições da pilha
        for i in 0 to 10 loop 
          PilhaNumero(i) <= 0;
        end loop;

        if(enterN = '0') then
          PN <= DN;
        else
          PN <= UN;
        end if;
        
        if(enterS = '0') then
          PS <= DS;
        else
          PS <= US; 
        end if;

      elsif (enterN = '1' and PN = DN) then
        PilhaNumero(cnt+1) <= to_integer(unsigned(numero)); --converter o número da entrada para decimal
        cnt := cnt + 1;
        init <= 1;
        PN <= UN;
      elsif (enterN = '0' and PN = UN) then
        PN <= DN;

      elsif (enterS = '1' and PS = DS and cnt > -1) then
        -- realiza as operacoes e joga o resultado na pilha
          if (sinal = "00" and cnt > 0) then --verifica se for o sinal de +
            PilhaNumero(cnt - 1) <= (PilhaNumero(cnt - 1) + PilhaNumero(cnt));
            init <= 1;
            cnt := cnt - 1;
          elsif (sinal = "01" and cnt > 0) then --verifica se for o sinal de -
            PilhaNumero(cnt - 1) <= (PilhaNumero(cnt - 1) - PilhaNumero(cnt));
            init <= 1;
            cnt := cnt - 1;
          elsif (sinal = "10") then --verifica se for o sinal de uma operacao de deslocamento
            PilhaNumero(cnt) <= (PilhaNumero(cnt) * 2);
            init <= 1;
          elsif (sinal = "11") then --verifica se for o sinal de >> (deslocamento para direita)
            PilhaNumero(cnt) <= (PilhaNumero(cnt)/2);
            init <=1;
          end if;
          PS <= US;
      elsif (enterS = '0' and PS = US) then
        PS <= DS; -- Down state
      end if;

      if(init = 1 ) then
        init <= 0;
        if(PilhaNumero(cnt)<0) then --instancia display negativos

          if(PilhaNumero(cnt)<-99) then
            cent <= PilhaNumero(cnt)/(-100);
            dec <= (PilhaNumero(cnt)*(-1)-(PilhaNumero(cnt)/(-100))*100)/10;
            unid <= PilhaNumero(cnt)*(-1) mod 10;
          elsif (PilhaNumero(cnt)< -9) then
            cent <= 10; --deliga o HEX2
            dec <= PilhaNumero(cnt)/(-10);
          else
            cent <= 10; --deliga o HEX2
            dec <= 10; --deliga o HEX1
          end if;

          HEX3 <= "10111111"; --coloca o sinal -
          unid <= PilhaNumero(cnt)*(-1) mod 10;

        else --instância display positivo

          if(PilhaNumero(cnt)>99) then
            cent <= PilhaNumero(cnt)/100;
            dec <= (PilhaNumero(cnt)-(PilhaNumero(cnt)/100)*100)/10;
          elsif(PilhaNumero(cnt)>9) then
            cent <= 10; --deliga o HEX2
            dec <= PilhaNumero(cnt)/10;
          else
            cent <= 10; --deliga o HEX2
            dec <= 10; --deliga o HEX1
          end if;

          unid <= PilhaNumero(cnt) mod 10;
          HEX3 <= "11111111";
        end if;

      end if;
    end if;  
  end process sync_proc;

end hardware;

tb_calc.vhd
-- library declaration
library IEEE;
use IEEE.std_logic_1164.all;

-- top-level entity
entity tb_calc is end entity;

-- architecture
architecture hardware of tb_calc is
  -- component declaration

  component calc is
    port (
      reset, clk, enterN, enterS: in std_logic;
      numero : in std_logic_vector(3 downto 0);
      sinal : in std_logic_vector(1 downto 0);
      HEX0, HEX1, HEX2, HEX3: out std_logic_vector (7 downto 0)
    );
  end component;

  constant PERIODO : time := 20 ns;
  signal ENT_CLK : std_logic := '0'; -- deve ser inicializado
  signal ENT_CLK_ENABLE : std_logic := '1'; -- Sinal de Enable do clock só para efeito de controle do fim da simulação
  signal ENT_RESET, ENT_ENTERN, ENT_ENTERS: std_logic;
  signal ENT_NUM : std_logic_vector(3 downto 0);
  signal ENT_SINAL : std_logic_vector(1 downto 0);
  signal ENT_H0, ENT_H1, ENT_H2, ENT_H3: std_logic_vector (7 downto 0);

begin
  -- geração do clock com periodo PERIODO
  ENT_CLK <= ENT_CLK_ENABLE and not ENT_CLK after PERIODO/2;
  ENT_CLK_ENABLE <= '1', '0' after 50*PERIODO; -- a simulação termina após transcorrer 20 períodos de clock.

  -- instanciação do DUT, que nesse exemplo é um ffd
  DUT : calc port map(clk => ENT_CLK, reset => ENT_RESET, numero => ENT_NUM, sinal => ENT_SINAL, enterN => ENT_ENTERN, enterS => ENT_ENTERS,
                       HEX0 => ENT_H0, HEX1 => ENT_H1, HEX2 => ENT_H2, HEX3 => ENT_H3);
  -- a partir daqui declaro os estímulos de entrada, ou a injecao de sinais
  -- um process para o reset
  reset : process
  begin
    ENT_RESET <= '1';
    wait for 2 * PERIODO; -- um reset de duração de 2 períodos de clock
    ENT_RESET <= '0';
    wait;
  end process reset;

  stimulus: process
  begin

    ENT_ENTERN <= '0';
    ENT_ENTERS <= '0';
    ENT_NUM <= "0101";
    wait for 2*PERIODO;
    ENT_ENTERN <= '1';
    wait for 4*PERIODO;
    ENT_ENTERN <= '0';
    wait for 2*PERIODO;
    ENT_NUM <= "0110";
    ENT_ENTERN <= '1';
    wait for 2*PERIODO;
    ENT_SINAL <= "10"; --DESLOCAMENTO PARA ESQUERDA
    ENT_ENTERS <= '1';
    wait for 2*PERIODO;
    ENT_ENTERS <= '0';
    wait for 2*PERIODO;
    ENT_ENTERN <= '0';
    ENT_SINAL <= "01"; --ADICAO
    ENT_ENTERS <= '1';
    wait for 2*PERIODO;
    ENT_ENTERS <= '0';
    wait for 3*PERIODO;
    ENT_NUM <= "1000";
    ENT_ENTERN <= '1';
    wait for 3*PERIODO;
    ENT_ENTERN <= '0';
    ENT_ENTERS <= '1';
    ENT_SINAL <= "01"; -- SUBTRACAO
    wait for 3*PERIODO;
    ENT_ENTERN <= '0';
    ENT_ENTERS <= '0';
    wait;
  end process stimulus;
end architecture;

tb_calc.vcd
$date
  Wed Dec 07 18:55:58 2022
$end
$version
  GHDL v0
$end
$timescale
  1 fs
$end
$scope module standard $end
$upscope $end
$scope module std_logic_1164 $end
$upscope $end
$scope module numeric_std $end
$upscope $end
$scope module tb_calc $end
$var reg 1 ! ent_clk $end
$var reg 1 " ent_clk_enable $end
$var reg 1 # ent_reset $end
$var reg 1 $ ent_entern $end
$var reg 1 % ent_enters $end
$var reg 4 & ent_num[3:0] $end
$var reg 2 ' ent_sinal[1:0] $end
$var reg 8 ( ent_h0[7:0] $end
$var reg 8 ) ent_h1[7:0] $end
$var reg 8 * ent_h2[7:0] $end
$var reg 8 + ent_h3[7:0] $end
$scope module dut $end
$var reg 1 , reset $end
$var reg 1 - clk $end
$var reg 1 . entern $end
$var reg 1 / enters $end
$var reg 4 0 numero[3:0] $end
$var reg 2 1 sinal[1:0] $end
$var reg 8 2 hex0[7:0] $end
$var reg 8 3 hex1[7:0] $end
$var reg 8 4 hex2[7:0] $end
$var reg 8 5 hex3[7:0] $end
$comment ps is not handled $end
$comment pn is not handled $end
$comment pilhanumero is not handled $end
$var integer 32 6 unid $end
$var integer 32 7 dec $end
$var integer 32 8 cent $end
$var integer 32 9 init $end
$scope module x1 $end
$var integer 32 : num $end
$var reg 8 ; hex[7:0] $end
$upscope $end
$scope module x2 $end
$var integer 32 < num $end
$var reg 8 = hex[7:0] $end
$upscope $end
$scope module x3 $end
$var integer 32 > num $end
$var reg 8 ? hex[7:0] $end
$upscope $end
$upscope $end
$upscope $end
$enddefinitions $end
#0
0!
1"
1#
0$
0%
b0101 &
bUU '
b11111111 (
b11111111 )
b11111111 *
bUUUUUUUU +
1,
0-
0.
0/
b0101 0
bUU 1
b11111111 2
b11111111 3
b11111111 4
bUUUUUUUU 5
b1010 6
b1010 7
b1010 8
b1010 9
b1010 :
b11111111 ;
b1010 <
b11111111 =
b1010 >
b11111111 ?
#10000000
1!
b11000000 (
b11111111 +
1-
b11000000 2
b11111111 5
b0 6
b0 9
b0 :
b11000000 ;
#20000000
0!
0-
#30000000
1!
1-
#40000000
0!
0#
1$
0,
0-
1.
#50000000
1!
1-
b1 9
#60000000
0!
0-
#70000000
1!
b10010010 (
1-
b10010010 2
b101 6
b0 9
b101 :
b10010010 ;
#80000000
0!
0-
#90000000
1!
1-
#100000000
0!
0-
#110000000
1!
1-
#120000000
0!
0$
0-
0.
#130000000
1!
1-
#140000000
0!
0-
#150000000
1!
1-
#160000000
0!
1$
b0110 &
0-
1.
b0110 0
#170000000
1!
1-
b1 9
#180000000
0!
0-
#190000000
1!
b10000010 (
1-
b10000010 2
b110 6
b0 9
b110 :
b10000010 ;
#200000000
0!
0$
1%
b00 '
0-
0.
1/
b00 1
#210000000
1!
1-
#220000000
0!
0-
#230000000
1!
1-
b1 9
#240000000
0!
0%
0-
0/
#250000000
1!
b11111001 (
b11111001 )
1-
b11111001 2
b11111001 3
b1 6
b1 7
b0 9
b1 :
b11111001 ;
b1 <
b11111001 =
#260000000
0!
0-
#270000000
1!
1-
#280000000
0!
0-
#290000000
1!
1-
#300000000
0!
1$
b0111 &
0-
1.
b0111 0
#310000000
1!
1-
b1 9
#320000000
0!
0-
#330000000
1!
b11111000 (
b11111111 )
1-
b11111000 2
b11111111 3
b111 6
b1010 7
b0 9
b111 :
b11111000 ;
b1010 <
b11111111 =
#340000000
0!
0-
#350000000
1!
1-
#360000000
0!
0$
1%
b01 '
0-
0.
1/
b01 1
#370000000
1!
1-
#380000000
0!
0-
#390000000
1!
1-
b1 9
#400000000
0!
0-
#410000000
1!
b10011001 (
1-
b10011001 2
b100 6
b0 9
b100 :
b10011001 ;
#420000000
0!
0%
0-
0/
